cwclientlib/__init__.py
cwclientlib/__pkginfo__.py
cwclientlib/builders.py
cwclientlib/cwcompleter.py
cwclientlib/cwget.py
cwclientlib/cwproxy.py
cwclientlib/cwrql.py
cwclientlib/cwshell.py
cwclientlib/cwupdate.py
cwclientlib/exceptions.py
cwclientlib/test/__init__.py
cwclientlib/test/test_cwproxy.py
cwclientlib/test/test_cwproxy_for.py
cwclientlib/test/data/bootstrap_cubes
cwclientlib/test/data/schema.py
cwclientlib/test/data/views.py
cwclientlib-1.6.0.dist-info/licenses/COPYING.LESSER
cwclientlib-1.6.0.dist-info/METADATA
cwclientlib-1.6.0.dist-info/WHEEL
cwclientlib-1.6.0.dist-info/entry_points.txt
cwclientlib-1.6.0.dist-info/top_level.txt
cwclientlib-1.6.0.dist-info/RECORD
