Metadata-Version: 2.4
Name: cwclientlib
Version: 1.6.0
Summary: A Python library to easily build CubicWeb clients
Home-page: https://forge.extranet.logilab.fr/cubicweb/cwclientlib
Author: LOGILAB S.A. (Paris, FRANCE)
Author-email: contact@logilab.fr
License: LGPL
Classifier: Environment :: Web Environment
Classifier: Framework :: CubicWeb
Classifier: Programming Language :: Python
Classifier: Programming Language :: Python :: 3
Classifier: Programming Language :: Python :: 3 :: Only
Requires-Python: >=3.11
License-File: COPYING.LESSER
Requires-Dist: requests>=2
Requires-Dist: logilab.common>=2
Requires-Dist: babel<3.0,>=2.17
Provides-Extra: yaml
Requires-Dist: PyYAML; extra == "yaml"
Dynamic: author
Dynamic: author-email
Dynamic: classifier
Dynamic: description
Dynamic: home-page
Dynamic: license
Dynamic: license-file
Dynamic: provides-extra
Dynamic: requires-dist
Dynamic: requires-python
Dynamic: summary
